<?xml version="1.0" encoding="UTF-8" standalone="no"?><Invoice xmlns="urn:oasis:names:specification:ubl:schema:xsd:Invoice-2" xmlns:cac="urn:oasis:names:specification:ubl:schema:xsd:CommonAggregateComponents-2" xmlns:cbc="urn:oasis:names:specification:ubl:schema:xsd:CommonBasicComponents-2" xmlns:cdt="urn:DocumentInformation:names:specification:ubl:colombia:schema:xsd:DocumentInformationAggregateComponents-1" xmlns:chl="urn:carvajal:names:specification:ubl:colombia:schema:xsd:CarvajalHealthComponents-1" xmlns:clm54217="urn:un:unece:uncefact:codelist:specification:54217:2001" xmlns:clm66411="urn:un:unece:uncefact:codelist:specification:66411:2001" xmlns:clmIANAMIMEMediaType="urn:un:unece:uncefact:codelist:specification:IANAMIMEMediaType:2003" xmlns:cts="urn:carvajal:names:specification:ubl:colombia:schema:xsd:CarvajalAggregateComponents-1" xmlns:ds="http://www.w3.org/2000/09/xmldsig#" xmlns:ext="urn:oasis:names:specification:ubl:schema:xsd:CommonExtensionComponents-2" xmlns:grl="urn:General:names:specification:ubl:colombia:schema:xsd:GeneralAggregateComponents-1" xmlns:ipt="urn:DocumentInformation:names:specification:ubl:colombia:schema:xsd:InteroperabilidadPT-1" xmlns:qdt="urn:oasis:names:specification:ubl:schema:xsd:QualifiedDatatypes-2" xmlns:sts="dian:gov:co:facturaelectronica:Structures-2-1" xmlns:udt="urn:un:unece:uncefact:data:specification:UnqualifiedDataTypesSchemaModule:2" xmlns:xades="http://uri.etsi.org/01903/v1.3.2#" xmlns:xades141="http://uri.etsi.org/01903/v1.4.1#" xmlns:xsi="http://www.w3.org/2001/XMLSchema-instance" xsi:schemaLocation="urn:oasis:names:specification:ubl:schema:xsd:Invoice-2 http://docs.oasis-open.org/ubl/os-UBL-2.1/xsd/maindoc/UBL-Invoice-2.1.xsd"><ext:UBLExtensions><ext:UBLExtension><ext:ExtensionContent><sts:DianExtensions><sts:InvoiceControl><sts:InvoiceAuthorization>18764080670228</sts:InvoiceAuthorization><sts:AuthorizationPeriod><cbc:StartDate>2024-10-01</cbc:StartDate><cbc:EndDate>2026-04-01</cbc:EndDate></sts:AuthorizationPeriod><sts:AuthorizedInvoices><sts:Prefix>CALI</sts:Prefix><sts:From>3483683</sts:From><sts:To>4500000</sts:To></sts:AuthorizedInvoices></sts:InvoiceControl><sts:InvoiceSource><cbc:IdentificationCode listAgencyID="6" listAgencyName="United Nations Economic Commission for Europe" listSchemeURI="urn:oasis:names:specification:ubl:codelist:gc:CountryIdentificationCode-2.1">CO</cbc:IdentificationCode></sts:InvoiceSource><sts:SoftwareProvider><sts:ProviderID schemeAgencyID="195" schemeAgencyName="CO, DIAN (Dirección de Impuestos y Aduanas Nacionales)" schemeID="0" schemeName="31">890321151</sts:ProviderID><sts:SoftwareID schemeAgencyID="195" schemeAgencyName="CO, DIAN (Dirección de Impuestos y Aduanas Nacionales)">eb9d23d3-f109-42b3-aa4e-394e22481a69</sts:SoftwareID></sts:SoftwareProvider><sts:SoftwareSecurityCode schemeAgencyID="195" schemeAgencyName="CO, DIAN (Dirección de Impuestos y Aduanas Nacionales)">dd0e082110f8fb8637a9677d0fe7d334711da7766dc03c62e63916a320335195a7dc0eddb1cab4d9d94ebb4564657eb7</sts:SoftwareSecurityCode><sts:AuthorizationProvider><sts:AuthorizationProviderID schemeAgencyID="195" schemeAgencyName="CO, DIAN (Dirección de Impuestos y Aduanas Nacionales)" schemeID="4" schemeName="31">800197268</sts:AuthorizationProviderID></sts:AuthorizationProvider><sts:QRCode>https://catalogo-vpfe.dian.gov.co/document/searchqr?documentkey=1fb4adda0de76856a51741b5145708dd8fcd7a09dcaee5772380783fb185a5007c5e78c72b0cf8b136b57559dcd3ac65</sts:QRCode></sts:DianExtensions></ext:ExtensionContent></ext:UBLExtension><ext:UBLExtension><ext:ExtensionContent><cts:AdditionalDocumentInformation><cts:Header><cts:PDFTemplate>CGEN04</cts:PDFTemplate></cts:Header><cts:Items><cts:Item><cts:LineNumber>1</cts:LineNumber></cts:Item><cts:Item><cts:LineNumber>2</cts:LineNumber></cts:Item><cts:Item><cts:LineNumber>3</cts:LineNumber></cts:Item><cts:Item><cts:LineNumber>4</cts:LineNumber></cts:Item><cts:Item><cts:LineNumber>5</cts:LineNumber></cts:Item></cts:Items></cts:AdditionalDocumentInformation></ext:ExtensionContent></ext:UBLExtension><ext:UBLExtension><ext:ExtensionContent><cdt:AdditionalDocumentInformation><cdt:Header><cdt:DocumentType>INVOIC</cdt:DocumentType></cdt:Header></cdt:AdditionalDocumentInformation></ext:ExtensionContent></ext:UBLExtension><ext:UBLExtension><ext:ExtensionContent><grl:AdditionalInformationGeneral><grl:Header><grl:AccountingSupplierParty><grl:Party><grl:PartyIdentificationID>890110964</grl:PartyIdentificationID></grl:Party></grl:AccountingSupplierParty><grl:AccountingCustomerParty><grl:Party/></grl:AccountingCustomerParty></grl:Header><grl:Items><grl:Item><grl:LineNumber>1</grl:LineNumber></grl:Item><grl:Item><grl:LineNumber>2</grl:LineNumber></grl:Item><grl:Item><grl:LineNumber>3</grl:LineNumber></grl:Item><grl:Item><grl:LineNumber>4</grl:LineNumber></grl:Item><grl:Item><grl:LineNumber>5</grl:LineNumber></grl:Item></grl:Items></grl:AdditionalInformationGeneral></ext:ExtensionContent></ext:UBLExtension><ext:UBLExtension><ext:ExtensionContent><ds:Signature Id="xmldsig-9e068324-7791-4a75-b382-2607bbff11cc">
<ds:SignedInfo>
<ds:CanonicalizationMethod Algorithm="http://www.w3.org/TR/2001/REC-xml-c14n-20010315"/>
<ds:SignatureMethod Algorithm="http://www.w3.org/2001/04/xmldsig-more#rsa-sha256"/>
<ds:Reference Id="xmldsig-9e068324-7791-4a75-b382-2607bbff11cc-ref0" URI="">
<ds:Transforms>
<ds:Transform Algorithm="http://www.w3.org/2000/09/xmldsig#enveloped-signature"/>
</ds:Transforms>
<ds:DigestMethod Algorithm="http://www.w3.org/2001/04/xmlenc#sha256"/>
<ds:DigestValue>3SSQ++pYUwhcm0zrBj/zQ/iMfvM7yJXR1thF/hKCrjU=</ds:DigestValue>
</ds:Reference>
<ds:Reference URI="#xmldsig-9e068324-7791-4a75-b382-2607bbff11cc-keyinfo">
<ds:DigestMethod Algorithm="http://www.w3.org/2001/04/xmlenc#sha256"/>
<ds:DigestValue>oeDU/lUD5Z/7OiODFozOJASwkEsIUVcC2q7YT6kV2Vw=</ds:DigestValue>
</ds:Reference>
<ds:Reference Type="http://uri.etsi.org/01903#SignedProperties" URI="#xmldsig-9e068324-7791-4a75-b382-2607bbff11cc-signedprops">
<ds:DigestMethod Algorithm="http://www.w3.org/2001/04/xmlenc#sha256"/>
<ds:DigestValue>vtJ9SdieY4mJeSr42xamcG/ueo3ifRSoY32LtkKtpPM=</ds:DigestValue>
</ds:Reference>
</ds:SignedInfo>
<ds:SignatureValue Id="xmldsig-9e068324-7791-4a75-b382-2607bbff11cc-sigvalue">
f8lFu56uiaeL/dADPyxto5EZYx0K3OqhQKEx5wdICMqnZU1YFjktTBNg+Z3dm2lLoWAiEJATVInn
CHMA25dmqMuCx8O9uTPOl5HWzIjmFq//eZUba3xdGHM1VR8lsHOx532UMNPJZmRs8Cq2WVCuUAKp
wYUpiYI3H4HijPCn5x1EE4lSB5c5bOHwqLiIn8/mxTQbVWU5lYFsf86bVsZLrYgBHVYHhC7waetz
COf1FMgTafw/IuHObDfgZjCRrUs82s99zbJo/NYZ2UwDMeDvs+LIRhufZSV6Gy+cYW+oxk93Q6VT
a9m0CUNK4fxSnHyuGCYhgL5jRU91wofQtM6VoQ==
</ds:SignatureValue>
<ds:KeyInfo Id="xmldsig-9e068324-7791-4a75-b382-2607bbff11cc-keyinfo">
<ds:X509Data>
<ds:X509Certificate>
MIIH0TCCBbmgAwIBAgIIU4M6V+laRrEwDQYJKoZIhvcNAQELBQAwgbYxIzAhBgkqhkiG9w0BCQEW
FGluZm9AYW5kZXNzY2QuY29tLmNvMSYwJAYDVQQDEx1DQSBBTkRFUyBTQ0QgUy5BLiBDbGFzZSBJ
SSB2MzEwMC4GA1UECxMnRGl2aXNpb24gZGUgY2VydGlmaWNhY2lvbiBlbnRpZGFkIGZpbmFsMRIw
EAYDVQQKEwlBbmRlcyBTQ0QxFDASBgNVBAcTC0JvZ290YSBELkMuMQswCQYDVQQGEwJDTzAeFw0y
NTA0MDQxNTIzNTVaFw0yNzA0MDQxNTIyNTVaMIIBJTEfMB0GA1UECQwWQ0wgMjkgTk9SVEUgIyA2
IEEgLSA0MDErMCkGCSqGSIb3DQEJARYcU2VndXJpZGFkMk5pdmVsQGNhcnZhamFsLmNvbTEzMDEG
A1UEAxMqQ0FSVkFKQUwgVEVDTk9MT0dJQSBZIFNFUlZJQ0lPUyBTLkEuUy4gQklDMRMwEQYDVQQF
Ewo4OTAzMjExNTEwMRkwFwYDVQQMExBQRVJTT05BIEpVUklESUNBMTowOAYDVQQLEzFFbWl0aWRv
IHBvciBBbmRlcyBTQ0QgQWMgMjYgNjlDIDAzIFRvcnJlIEIgT2YgNzAxMQ0wCwYDVQQHEwRDQUxJ
MRgwFgYDVQQIEw9WQUxMRSBERUwgQ0FVQ0ExCzAJBgNVBAYTAkNPMIIBIjANBgkqhkiG9w0BAQEF
AAOCAQ8AMIIBCgKCAQEAuAaL9NSi2JvVg3QKOs3wzfrVRAX4FXw6zKRTNJ/8JtHa98n9MeiNDonL
xPlUqnVdpIYP41tDBwv3XXqVMZCOe8jE+YgSTIAvca03ql9nXRNf5z7CW4qMOFDUw1rNVstopyCQ
DyB4OQlRX3Z2ATSGzbrTJXUnW0DNJWkVIA+B1toKtM7bZGHYZe0fnFNawTUU8TMXwgl9D/h7gMfb
f5Ies1g4MT1eFj+eomba5MJl8bLAmdS8dxUi4CX8HrBSknhT0v9AT/DHJPe2UreidykYEByg3e3W
CpF24PpqX8BKRoaZiYFUqSDERUk5YALcRgAcGVGXje3QttmgVbPLgvuVIwIDAQABo4ICbzCCAmsw
DAYDVR0TAQH/BAIwADAfBgNVHSMEGDAWgBRA/iZpRzInMtGsIcgu7M+N1TVo6DBvBggrBgEFBQcB
AQRjMGEwNgYIKwYBBQUHMAKGKmh0dHA6Ly9jZXJ0cy5hbmRlc3NjZC5jb20uY28vQ2xhc2VJSXYz
LmNydDAnBggrBgEFBQcwAYYbaHR0cDovL29jc3AuYW5kZXNzY2QuY29tLmNvMCcGA1UdEQQgMB6B
HFNlZ3VyaWRhZDJOaXZlbEBjYXJ2YWphbC5jb20wggEVBgNVHSAEggEMMIIBCDCBuAYMKwYBBAGB
9EgBAgkMMIGnMIGkBggrBgEFBQcCAjCBlwyBlExhIHV0aWxpemFjacOzbiBkZSBlc3RlIGNlcnRp
ZmljYWRvIGVzdMOhIHN1amV0YSBhIGxhIFBDIGRlIFBlcnNvbmEgSnVyw61kaWNhIHkgRFBDIGVz
dGFibGVjaWRhcyBwb3IgQW5kZXMgU0NELiBDw7NkaWdvIGRlIEFjcmVkaXRhY2nDs246IDE2LUVD
RC0wMDQwSwYMKwYBBAGB9EgBAQENMDswOQYIKwYBBQUHAgEWLWh0dHBzOi8vYW5kZXNzY2QuY29t
LmNvL2RvY3MvRFBDX0FuZGVzU0NELnBkZjAdBgNVHSUEFjAUBggrBgEFBQcDAgYIKwYBBQUHAwQw
OQYDVR0fBDIwMDAuoCygKoYoaHR0cDovL2NybC5hbmRlc3NjZC5jb20uY28vQ2xhc2VJSXYzLmNy
bDAdBgNVHQ4EFgQU9KiES91gKk8PPigQ/jQZHf4BoegwDgYDVR0PAQH/BAQDAgTwMA0GCSqGSIb3
DQEBCwUAA4ICAQCEdcHg7fJzhpKQgVcsCuLJUg9TWmDxxiwfU3lK2CWjEzQxBYLJS9TtQsQEtQpp
ed1ggFYxSbhF92+VbxFN12j8vJg7rDJFSGFosHAF1t0WYyvFL8Dc9GD2kj6WR6TUpuRyQaML/IpB
O1gW/VHZQBzsgvW1LbCAMZyGnOjUJHWiRKyrfclFsNNDglwN7/IV+xSh7vjgQqOge3Gkrq9mMbv4
vvpaJJQxUTn4ysFfPbzm4QJtoe16PguGNjwCOkLnXIELmMoVTh+iDWJkrDIOWcF7gpVR4XQhWobl
YfU5ejIAXlQaTyh1HKweQFtoMcRNZ5O8YVXWVtL2gLbeYmYsXGLcRj2evs6sLTjUinRW65hfjuJ4
PpJVyS3lEVmZTZ/iyD8VPEEmD7HwK5oAgf2lxwIwyfFq+t+kAHp+U/fJIdDuviBVkev/xuFgTkSa
2I2vkSjXN7RyYlz730U0QoQDhMkhRTDu+qai9BpG64MfTXfaFhmgqdyZl0ZAGJAWcDylgofQRj26
58k7arKRNcpM4vHzTaIFuiRpOx/x32P7H+hOYBQryGwRqo9Tbd3yQ5kWCk3fNc/fEk5a6Rg984I8
GXxEt9BiWQZ/kEukEcEv09drvnIrZJSbjLLOc7oAlRzknmYCHKCFsYGFglcWfYu5jMoBL1zbQ8a0
KVP/sDhqPhDfyg==
</ds:X509Certificate>
</ds:X509Data>
</ds:KeyInfo>
<ds:Object><xades:QualifyingProperties Target="#xmldsig-9e068324-7791-4a75-b382-2607bbff11cc"><xades:SignedProperties Id="xmldsig-9e068324-7791-4a75-b382-2607bbff11cc-signedprops"><xades:SignedSignatureProperties><xades:SigningTime>2025-04-29T19:37:53.707-05:00</xades:SigningTime><xades:SigningCertificate><xades:Cert><xades:CertDigest><ds:DigestMethod Algorithm="http://www.w3.org/2001/04/xmlenc#sha256"/><ds:DigestValue>7UTaN50sIhoCD/nz7cYitqmRCUT77kkinCg+rOczmaU=</ds:DigestValue></xades:CertDigest><xades:IssuerSerial><ds:X509IssuerName>C=CO,L=Bogota D.C.,O=Andes SCD,OU=Division de certificacion entidad final,CN=CA ANDES SCD S.A. Clase II v3,1.2.840.113549.1.9.1=#1614696e666f40616e6465737363642e636f6d2e636f</ds:X509IssuerName><ds:X509SerialNumber>6017717676348688049</ds:X509SerialNumber></xades:IssuerSerial></xades:Cert><xades:Cert><xades:CertDigest><ds:DigestMethod Algorithm="http://www.w3.org/2001/04/xmlenc#sha256"/><ds:DigestValue>RLYziy/D+T4pgDLc65EboYLzIoC/iYCwrOCGzGo/MO0=</ds:DigestValue></xades:CertDigest><xades:IssuerSerial><ds:X509IssuerName>C=CO,L=Bogota D.C.,O=Andes SCD,OU=Division de certificacion,CN=ROOT CA ANDES SCD S.A.,1.2.840.113549.1.9.1=#1614696e666f40616e6465737363642e636f6d2e636f</ds:X509IssuerName><ds:X509SerialNumber>6218172215901586992</ds:X509SerialNumber></xades:IssuerSerial></xades:Cert><xades:Cert><xades:CertDigest><ds:DigestMethod Algorithm="http://www.w3.org/2001/04/xmlenc#sha256"/><ds:DigestValue>Cs7emRwtXWVYHJrqS9eXEXfUcFyJJBqFhDFOetHu8ts=</ds:DigestValue></xades:CertDigest><xades:IssuerSerial><ds:X509IssuerName>C=CO,L=Bogota D.C.,O=Andes SCD,OU=Division de certificacion,CN=ROOT CA ANDES SCD S.A.,1.2.840.113549.1.9.1=#1614696e666f40616e6465737363642e636f6d2e636f</ds:X509IssuerName><ds:X509SerialNumber>3184328748892787122</ds:X509SerialNumber></xades:IssuerSerial></xades:Cert></xades:SigningCertificate><xades:SignaturePolicyIdentifier><xades:SignaturePolicyId><xades:SigPolicyId><xades:Identifier>https://facturaelectronica.dian.gov.co/politicadefirma/v2/politicadefirmav2.pdf</xades:Identifier></xades:SigPolicyId><xades:SigPolicyHash><ds:DigestMethod Algorithm="http://www.w3.org/2001/04/xmlenc#sha256"/><ds:DigestValue>dMoMvtcG5aIzgYo0tIsSQeVJBDnUnfSOfBpxXrmor0Y=</ds:DigestValue></xades:SigPolicyHash></xades:SignaturePolicyId></xades:SignaturePolicyIdentifier><xades:SignerRole><xades:ClaimedRoles><xades:ClaimedRole>third party</xades:ClaimedRole></xades:ClaimedRoles></xades:SignerRole></xades:SignedSignatureProperties></xades:SignedProperties></xades:QualifyingProperties></ds:Object>
</ds:Signature></ext:ExtensionContent></ext:UBLExtension></ext:UBLExtensions><cbc:UBLVersionID>UBL 2.1</cbc:UBLVersionID><cbc:CustomizationID schemeID="">10</cbc:CustomizationID><cbc:ProfileID>DIAN 2.1: Factura Electrónica de Venta</cbc:ProfileID><cbc:ProfileExecutionID>1</cbc:ProfileExecutionID><cbc:ID>CALI3780551</cbc:ID><cbc:UUID schemeID="1" schemeName="CUFE-SHA384">1fb4adda0de76856a51741b5145708dd8fcd7a09dcaee5772380783fb185a5007c5e78c72b0cf8b136b57559dcd3ac65</cbc:UUID><cbc:IssueDate>2025-04-29</cbc:IssueDate><cbc:IssueTime>17:17:08-05:00</cbc:IssueTime><cbc:DueDate>2025-04-29</cbc:DueDate><cbc:InvoiceTypeCode>01</cbc:InvoiceTypeCode><cbc:Note>1.-IVA REGIMEN COMUN - AGENTES RETENEDORES DE IVA.|SOMOS GRANDES CONTRIBUYENTES|(RES. DIAN No. 012220 - 26 DIC 2022).|SOMOS AUTORETE. DE RENTA (RES.DIAN10574 NOV. 09/05)|RESOLUCION FACTURACION ELECTRONICA 18764080670228 |FECHA ( 01/10/2024 ) DEL : CALI3483683 - CALI4500000 | VIGENCIA DE 18 MESES.</cbc:Note><cbc:Note>3.-PEDIDO R-SALES  ( DAUGW3X04TFAX0280425 )||CONDICIONES : 1.FAVOR VERIFICAR LA MERCANCIA EN EL MOMENTO DE RECIBIRLA|                         2.FAVOR GIRAR CHEQUE CRUZADO A NOMBRE DE ( ALIMENTOS DEL VALLE S.A. )||Políticas de Tratamiento de Datos Personales - www.alival.com.co||</cbc:Note><cbc:Note>8.-SUPERMARKET LA FLORA|3106335637                    </cbc:Note><cbc:Note>10.-11326</cbc:Note><cbc:Note>7.-www.alival.com.co</cbc:Note><cbc:Note>6.-|NOVENTA Y CINCO MIL CUATROCIENTOS OCHENTA Y OCHO PESOS</cbc:Note><cbc:Note>11.-|9</cbc:Note><cbc:Note>El ejemplar que reciba la DIAN se utilizará sólo para fines de control, verificación y fiscalización</cbc:Note><cbc:Note>NumFac: CALI3780551 FecFac: 2025-04-29 HorFac: 17:17:08-05:00 NitFac: 890110964 DocAdq: 1193415473 ValFac: 83106.00 ValIva: 12381.54 ValOtroIm: 0.00 ValTolFac: 95487.54 CUFE:  1fb4adda0de76856a51741b5145708dd8fcd7a09dcaee5772380783fb185a5007c5e78c72b0cf8b136b57559dcd3ac65 https://catalogo-vpfe.dian.gov.co/document/searchqr?documentkey=1fb4adda0de76856a51741b5145708dd8fcd7a09dcaee5772380783fb185a5007c5e78c72b0cf8b136b57559dcd3ac65</cbc:Note><cbc:Note>NumFac: CALI3780551 FecFac: 2025-04-29 HorFac: 17:17:08-05:00 ValFac: 95487.54 CodImp1: 01 ValImp1: 12381.54 CodImp2: 02 ValImp2: 0.00 CodImp3: 03 ValImp3: 0.00 ValTot: 83106.00 NitOFE: 890110964 NumAdq: 1193415473 TipoAmbiente: 1 String: CALI37805512025-04-2917:17:08-05:0083106.000112381.54040.00030.0095487.5489011096411934154731</cbc:Note><cbc:DocumentCurrencyCode>COP</cbc:DocumentCurrencyCode><cbc:LineCountNumeric>5</cbc:LineCountNumeric><cac:OrderReference><cbc:ID>DAUGW3X04TFAX0280425</cbc:ID><cbc:SalesOrderID>PEDIDO R-SALES</cbc:SalesOrderID></cac:OrderReference><cac:AdditionalDocumentReference><cbc:ID>11326</cbc:ID><cbc:IssueDate>2019-11-28</cbc:IssueDate><cbc:DocumentTypeCode>RF1</cbc:DocumentTypeCode><cbc:DocumentType>Información del emisor para filtros y visualización en Carvajal</cbc:DocumentType></cac:AdditionalDocumentReference><cac:AccountingSupplierParty><cbc:AdditionalAccountID>1</cbc:AdditionalAccountID><cac:Party><cac:PartyName><cbc:Name>ALIVAL S.A</cbc:Name></cac:PartyName><cac:PhysicalLocation><cac:Address><cbc:ID>19142</cbc:ID><cbc:CityName>CALOTO</cbc:CityName><cbc:PostalZone>191070</cbc:PostalZone><cbc:CountrySubentity>CAUCA</cbc:CountrySubentity><cbc:CountrySubentityCode>19</cbc:CountrySubentityCode><cac:AddressLine><cbc:Line>PARQUE INDUSTRIAL Y COMERCIAL DEL CAUCA, ETAPA 2 LOTE 5</cbc:Line></cac:AddressLine><cac:Country><cbc:IdentificationCode>CO</cbc:IdentificationCode><cbc:Name languageID="es">COLOMBIA</cbc:Name></cac:Country></cac:Address></cac:PhysicalLocation><cac:PartyTaxScheme><cbc:RegistrationName>ALIMENTOS DEL VALLE S.A</cbc:RegistrationName><cbc:CompanyID schemeAgencyID="195" schemeAgencyName="CO, DIAN (Dirección de Impuestos y Aduanas Nacionales)" schemeID="6" schemeName="31">890110964</cbc:CompanyID><cbc:TaxLevelCode listName="No aplica">O-13;O-15</cbc:TaxLevelCode><cac:RegistrationAddress><cbc:ID>19142</cbc:ID><cbc:CityName>CALOTO</cbc:CityName><cbc:PostalZone>191070</cbc:PostalZone><cbc:CountrySubentity>CAUCA</cbc:CountrySubentity><cbc:CountrySubentityCode>19</cbc:CountrySubentityCode><cac:AddressLine><cbc:Line>PARQUE INDUSTRIAL Y COMERCIAL DEL CAUCA, ETAPA 2 LOTE 5</cbc:Line></cac:AddressLine><cac:Country><cbc:IdentificationCode>CO</cbc:IdentificationCode><cbc:Name languageID="es">COLOMBIA</cbc:Name></cac:Country></cac:RegistrationAddress><cac:TaxScheme><cbc:ID>01</cbc:ID><cbc:Name>IVA</cbc:Name></cac:TaxScheme></cac:PartyTaxScheme><cac:PartyLegalEntity><cbc:RegistrationName>ALIMENTOS DEL VALLE S.A ALIVAL S.A</cbc:RegistrationName><cbc:CompanyID schemeAgencyID="195" schemeAgencyName="CO, DIAN (Dirección de Impuestos y Aduanas Nacionales)" schemeID="6" schemeName="31">890110964</cbc:CompanyID><cac:CorporateRegistrationScheme><cbc:ID>CALI</cbc:ID></cac:CorporateRegistrationScheme></cac:PartyLegalEntity><cac:Contact><cbc:Name>VENTAS - MERCADEO</cbc:Name><cbc:Telephone>8870404</cbc:Telephone><cbc:ElectronicMail>ventas@alival.com.co</cbc:ElectronicMail></cac:Contact></cac:Party></cac:AccountingSupplierParty><cac:AccountingCustomerParty><cbc:AdditionalAccountID>2</cbc:AdditionalAccountID><cac:Party><cac:PartyIdentification><cbc:ID schemeID="4" schemeName="13">1193415473</cbc:ID></cac:PartyIdentification><cac:PartyName><cbc:Name>JUAN RIVERA</cbc:Name></cac:PartyName><cac:PhysicalLocation><cac:Address><cbc:ID>76001</cbc:ID><cbc:CityName>VALLE DEL CAUCA</cbc:CityName><cbc:PostalZone>760001</cbc:PostalZone><cbc:CountrySubentity>CALI</cbc:CountrySubentity><cbc:CountrySubentityCode>76</cbc:CountrySubentityCode><cac:AddressLine><cbc:Line>CL 47 norte # 4 an-24</cbc:Line></cac:AddressLine><cac:Country><cbc:IdentificationCode>CO</cbc:IdentificationCode><cbc:Name languageID="es">COLOMBIA</cbc:Name></cac:Country></cac:Address></cac:PhysicalLocation><cac:PartyTaxScheme><cbc:RegistrationName>JUAN RIVERA</cbc:RegistrationName><cbc:CompanyID schemeAgencyID="195" schemeAgencyName="CO, DIAN (Dirección de Impuestos y Aduanas Nacionales)" schemeID="4" schemeName="13">1193415473</cbc:CompanyID><cbc:TaxLevelCode listName="No aplica">R-99-PN</cbc:TaxLevelCode><cac:TaxScheme><cbc:ID>01</cbc:ID><cbc:Name>IVA</cbc:Name></cac:TaxScheme></cac:PartyTaxScheme><cac:PartyLegalEntity><cbc:RegistrationName>JUAN RIVERA</cbc:RegistrationName><cbc:CompanyID schemeAgencyID="195" schemeAgencyName="CO, DIAN (Dirección de Impuestos y Aduanas Nacionales)" schemeID="4" schemeName="13">1193415473</cbc:CompanyID></cac:PartyLegalEntity><cac:Contact><cbc:Name>LOGISTICA GENERAL</cbc:Name><cbc:Telephone>3106335637                    </cbc:Telephone><cbc:ElectronicMail>.                                                                                                                       </cbc:ElectronicMail></cac:Contact><cac:Person><cbc:FirstName>JUAN</cbc:FirstName><cbc:FamilyName>RIVERA</cbc:FamilyName></cac:Person></cac:Party></cac:AccountingCustomerParty><cac:Delivery><cac:DeliveryAddress><cbc:ID>76001</cbc:ID><cbc:CityName>CALI</cbc:CityName><cbc:CountrySubentity>VALLE DEL CAUCA</cbc:CountrySubentity><cbc:CountrySubentityCode>76</cbc:CountrySubentityCode><cac:AddressLine><cbc:Line>CL 47 norte # 4 an-24</cbc:Line></cac:AddressLine><cac:Country><cbc:IdentificationCode>CO</cbc:IdentificationCode><cbc:Name languageID="es">COLOMBIA</cbc:Name></cac:Country></cac:DeliveryAddress><cac:DeliveryParty><cac:PartyName><cbc:Name>ALIMENTOS DEL VALLE S.A</cbc:Name></cac:PartyName><cac:PhysicalLocation><cac:Address><cbc:ID>19142</cbc:ID><cbc:CityName>CALOTO</cbc:CityName><cbc:PostalZone>191070</cbc:PostalZone><cbc:CountrySubentity>CAUCA</cbc:CountrySubentity><cbc:CountrySubentityCode>19</cbc:CountrySubentityCode><cac:AddressLine><cbc:Line>PARQUE INDUSTRIAL Y COMERCIAL DEL CAUCA, ETAPA 2 LOTE 5</cbc:Line></cac:AddressLine><cac:Country><cbc:IdentificationCode>CO</cbc:IdentificationCode><cbc:Name languageID="es">COLOMBIA</cbc:Name></cac:Country></cac:Address></cac:PhysicalLocation><cac:PartyTaxScheme><cbc:RegistrationName>ALIMENTOS DEL VALLE S.A</cbc:RegistrationName><cbc:CompanyID schemeAgencyID="195" schemeAgencyName="CO, DIAN (Dirección de Impuestos y Aduanas Nacionales)" schemeID="6" schemeName="31">890110964</cbc:CompanyID><cbc:TaxLevelCode listName="No aplica">O-13;O-15</cbc:TaxLevelCode><cac:RegistrationAddress><cbc:ID>19142</cbc:ID><cbc:CityName>CALOTO</cbc:CityName><cbc:CountrySubentity>CAUCA</cbc:CountrySubentity><cbc:CountrySubentityCode>19</cbc:CountrySubentityCode><cac:AddressLine><cbc:Line>PARQUE INDUSTRIAL Y COMERCIAL DEL CAUCA, ETAPA 2 LOTE 5</cbc:Line></cac:AddressLine><cac:Country><cbc:IdentificationCode>CO</cbc:IdentificationCode><cbc:Name languageID="es">COLOMBIA</cbc:Name></cac:Country></cac:RegistrationAddress><cac:TaxScheme><cbc:ID>01</cbc:ID><cbc:Name>IVA</cbc:Name></cac:TaxScheme></cac:PartyTaxScheme></cac:DeliveryParty></cac:Delivery><cac:PaymentMeans><cbc:ID schemeID="">1</cbc:ID><cbc:PaymentMeansCode>10</cbc:PaymentMeansCode><cbc:PaymentDueDate>2025-04-29</cbc:PaymentDueDate></cac:PaymentMeans><cac:AllowanceCharge><cbc:ID>1</cbc:ID><cbc:ChargeIndicator>false</cbc:ChargeIndicator><cbc:MultiplierFactorNumeric>0.00</cbc:MultiplierFactorNumeric><cbc:Amount currencyID="COP">0.00</cbc:Amount><cbc:BaseAmount currencyID="COP">83106.00</cbc:BaseAmount></cac:AllowanceCharge><cac:TaxTotal><cbc:TaxAmount currencyID="COP">12381.54</cbc:TaxAmount><cac:TaxSubtotal><cbc:TaxableAmount currencyID="COP">65166.00</cbc:TaxableAmount><cbc:TaxAmount currencyID="COP">12381.54</cbc:TaxAmount><cac:TaxCategory><cbc:Percent>19.00</cbc:Percent><cac:TaxScheme><cbc:ID>01</cbc:ID><cbc:Name>IVA</cbc:Name></cac:TaxScheme></cac:TaxCategory></cac:TaxSubtotal></cac:TaxTotal><cac:LegalMonetaryTotal><cbc:LineExtensionAmount currencyID="COP">83106.00</cbc:LineExtensionAmount><cbc:TaxExclusiveAmount currencyID="COP">65166.00</cbc:TaxExclusiveAmount><cbc:TaxInclusiveAmount currencyID="COP">95487.54</cbc:TaxInclusiveAmount><cbc:AllowanceTotalAmount currencyID="COP">0.00</cbc:AllowanceTotalAmount><cbc:PayableAmount currencyID="COP">95487.54</cbc:PayableAmount></cac:LegalMonetaryTotal><cac:InvoiceLine><cbc:ID schemeID="">1</cbc:ID><cbc:Note>ITE_10|6680.00</cbc:Note><cbc:Note>ITE_21|6680.00</cbc:Note><cbc:Note>ITE_22|COP</cbc:Note><cbc:InvoicedQuantity unitCode="94">1</cbc:InvoicedQuantity><cbc:LineExtensionAmount currencyID="COP">6680.00</cbc:LineExtensionAmount><cac:AllowanceCharge><cbc:ID>1</cbc:ID><cbc:ChargeIndicator>false</cbc:ChargeIndicator><cbc:MultiplierFactorNumeric>0.00</cbc:MultiplierFactorNumeric><cbc:Amount currencyID="COP">0.00</cbc:Amount><cbc:BaseAmount currencyID="COP">6680.00</cbc:BaseAmount></cac:AllowanceCharge><cac:TaxTotal><cbc:TaxAmount currencyID="COP">1269.20</cbc:TaxAmount><cac:TaxSubtotal><cbc:TaxableAmount currencyID="COP">6680.00</cbc:TaxableAmount><cbc:TaxAmount currencyID="COP">1269.20</cbc:TaxAmount><cac:TaxCategory><cbc:Percent>19.00</cbc:Percent><cac:TaxScheme><cbc:ID>01</cbc:ID><cbc:Name>IVA</cbc:Name></cac:TaxScheme></cac:TaxCategory></cac:TaxSubtotal></cac:TaxTotal><cac:Item><cbc:Description>JUGO TAMPICO CITRUS PUNCH  PET X 330 ML PAGUE 5 LLEVE 6</cbc:Description><cac:SellersItemIdentification><cbc:ID>17253</cbc:ID></cac:SellersItemIdentification><cac:StandardItemIdentification><cbc:ID schemeAgencyID="" schemeID="010" schemeName="">9</cbc:ID></cac:StandardItemIdentification></cac:Item><cac:Price><cbc:PriceAmount currencyID="COP">6680.00</cbc:PriceAmount><cbc:BaseQuantity unitCode="94">1</cbc:BaseQuantity></cac:Price></cac:InvoiceLine><cac:InvoiceLine><cbc:ID schemeID="">2</cbc:ID><cbc:Note>ITE_10|12974.00</cbc:Note><cbc:Note>ITE_21|12974.00</cbc:Note><cbc:Note>ITE_22|COP</cbc:Note><cbc:InvoicedQuantity unitCode="94">1</cbc:InvoicedQuantity><cbc:LineExtensionAmount currencyID="COP">12974.00</cbc:LineExtensionAmount><cac:AllowanceCharge><cbc:ID>2</cbc:ID><cbc:ChargeIndicator>false</cbc:ChargeIndicator><cbc:MultiplierFactorNumeric>0.00</cbc:MultiplierFactorNumeric><cbc:Amount currencyID="COP">0.00</cbc:Amount><cbc:BaseAmount currencyID="COP">12974.00</cbc:BaseAmount></cac:AllowanceCharge><cac:TaxTotal><cbc:TaxAmount currencyID="COP">2465.06</cbc:TaxAmount><cac:TaxSubtotal><cbc:TaxableAmount currencyID="COP">12974.00</cbc:TaxableAmount><cbc:TaxAmount currencyID="COP">2465.06</cbc:TaxAmount><cac:TaxCategory><cbc:Percent>19.00</cbc:Percent><cac:TaxScheme><cbc:ID>01</cbc:ID><cbc:Name>IVA</cbc:Name></cac:TaxScheme></cac:TaxCategory></cac:TaxSubtotal></cac:TaxTotal><cac:Item><cbc:Description>JUGO TAMPICO CITRUS PETX500 ML X 8 UNID. DSCTO 15%</cbc:Description><cac:SellersItemIdentification><cbc:ID>17578</cbc:ID></cac:SellersItemIdentification><cac:StandardItemIdentification><cbc:ID schemeAgencyID="" schemeID="010" schemeName="">9</cbc:ID></cac:StandardItemIdentification></cac:Item><cac:Price><cbc:PriceAmount currencyID="COP">12974.00</cbc:PriceAmount><cbc:BaseQuantity unitCode="94">1</cbc:BaseQuantity></cac:Price></cac:InvoiceLine><cac:InvoiceLine><cbc:ID schemeID="">3</cbc:ID><cbc:Note>ITE_10|13780.00</cbc:Note><cbc:Note>ITE_21|13780.00</cbc:Note><cbc:Note>ITE_22|COP</cbc:Note><cbc:InvoicedQuantity unitCode="94">1</cbc:InvoicedQuantity><cbc:LineExtensionAmount currencyID="COP">13780.00</cbc:LineExtensionAmount><cac:AllowanceCharge><cbc:ID>3</cbc:ID><cbc:ChargeIndicator>false</cbc:ChargeIndicator><cbc:MultiplierFactorNumeric>0.00</cbc:MultiplierFactorNumeric><cbc:Amount currencyID="COP">0.00</cbc:Amount><cbc:BaseAmount currencyID="COP">13780.00</cbc:BaseAmount></cac:AllowanceCharge><cac:TaxTotal><cbc:TaxAmount currencyID="COP">2618.20</cbc:TaxAmount><cac:TaxSubtotal><cbc:TaxableAmount currencyID="COP">13780.00</cbc:TaxableAmount><cbc:TaxAmount currencyID="COP">2618.20</cbc:TaxAmount><cac:TaxCategory><cbc:Percent>19.00</cbc:Percent><cac:TaxScheme><cbc:ID>01</cbc:ID><cbc:Name>IVA</cbc:Name></cac:TaxScheme></cac:TaxCategory></cac:TaxSubtotal></cac:TaxTotal><cac:Item><cbc:Description>JUGO TAMPICO CITRUS PET X 1000 ML. PAGUE 5 LLEVE 6</cbc:Description><cac:SellersItemIdentification><cbc:ID>17563</cbc:ID></cac:SellersItemIdentification><cac:StandardItemIdentification><cbc:ID schemeAgencyID="" schemeID="010" schemeName="">9</cbc:ID></cac:StandardItemIdentification></cac:Item><cac:Price><cbc:PriceAmount currencyID="COP">13780.00</cbc:PriceAmount><cbc:BaseQuantity unitCode="94">1</cbc:BaseQuantity></cac:Price></cac:InvoiceLine><cac:InvoiceLine><cbc:ID schemeID="">4</cbc:ID><cbc:Note>ITE_10|17940.00</cbc:Note><cbc:Note>ITE_21|17940.00</cbc:Note><cbc:Note>ITE_22|COP</cbc:Note><cbc:InvoicedQuantity unitCode="94">2</cbc:InvoicedQuantity><cbc:LineExtensionAmount currencyID="COP">17940.00</cbc:LineExtensionAmount><cac:AllowanceCharge><cbc:ID>4</cbc:ID><cbc:ChargeIndicator>false</cbc:ChargeIndicator><cbc:MultiplierFactorNumeric>0.00</cbc:MultiplierFactorNumeric><cbc:Amount currencyID="COP">0.00</cbc:Amount><cbc:BaseAmount currencyID="COP">17940.00</cbc:BaseAmount></cac:AllowanceCharge><cac:Item><cbc:Description>SOUR CREAM SANFERNANDO VASO X 400 GRS.</cbc:Description><cac:SellersItemIdentification><cbc:ID>11598</cbc:ID></cac:SellersItemIdentification><cac:StandardItemIdentification><cbc:ID schemeAgencyID="" schemeID="010" schemeName="">9</cbc:ID></cac:StandardItemIdentification></cac:Item><cac:Price><cbc:PriceAmount currencyID="COP">8970.00</cbc:PriceAmount><cbc:BaseQuantity unitCode="94">2</cbc:BaseQuantity></cac:Price></cac:InvoiceLine><cac:InvoiceLine><cbc:ID schemeID="">5</cbc:ID><cbc:Note>ITE_10|31732.00</cbc:Note><cbc:Note>ITE_21|31732.00</cbc:Note><cbc:Note>ITE_22|COP</cbc:Note><cbc:InvoicedQuantity unitCode="94">4</cbc:InvoicedQuantity><cbc:LineExtensionAmount currencyID="COP">31732.00</cbc:LineExtensionAmount><cac:AllowanceCharge><cbc:ID>5</cbc:ID><cbc:ChargeIndicator>false</cbc:ChargeIndicator><cbc:MultiplierFactorNumeric>0.00</cbc:MultiplierFactorNumeric><cbc:Amount currencyID="COP">0.00</cbc:Amount><cbc:BaseAmount currencyID="COP">31732.00</cbc:BaseAmount></cac:AllowanceCharge><cac:TaxTotal><cbc:TaxAmount currencyID="COP">6029.08</cbc:TaxAmount><cac:TaxSubtotal><cbc:TaxableAmount currencyID="COP">31732.00</cbc:TaxableAmount><cbc:TaxAmount currencyID="COP">6029.08</cbc:TaxAmount><cac:TaxCategory><cbc:Percent>19.00</cbc:Percent><cac:TaxScheme><cbc:ID>01</cbc:ID><cbc:Name>IVA</cbc:Name></cac:TaxScheme></cac:TaxCategory></cac:TaxSubtotal></cac:TaxTotal><cac:Item><cbc:Description>MANTEQUILLA SANFERNANDO CON SAL X 200 GR</cbc:Description><cac:SellersItemIdentification><cbc:ID>11701</cbc:ID></cac:SellersItemIdentification><cac:StandardItemIdentification><cbc:ID schemeAgencyID="" schemeID="010" schemeName="">9</cbc:ID></cac:StandardItemIdentification></cac:Item><cac:Price><cbc:PriceAmount currencyID="COP">7933.00</cbc:PriceAmount><cbc:BaseQuantity unitCode="94">4</cbc:BaseQuantity></cac:Price></cac:InvoiceLine></Invoice>